oscslip_proxy/__init__.py
oscslip_proxy/__main__.py
oscslip_proxy/osc_server.py
oscslip_proxy/serial_proxy.py
oscslip_proxy-0.0.2.dist-info/METADATA
oscslip_proxy-0.0.2.dist-info/WHEEL
oscslip_proxy-0.0.2.dist-info/entry_points.txt
oscslip_proxy-0.0.2.dist-info/licenses/LICENSE
oscslip_proxy-0.0.2.dist-info/RECORD
