Metadata-Version: 2.4
Name: oscslip-proxy
Version: 0.0.2
Summary: An OSC server that proxies between local network and SLIP-encoded OSC over serial
Project-URL: Homepage, https://codeberg.org/elgiano/oscslip-proxy
Project-URL: Issues, https://codeberg.org/elgiano/oscslip-proxy/issues
Author-email: Gianluca Elia <dev@gianlucaelia.eu>
License-Expression: Unlicense
License-File: LICENSE
Requires-Python: >=3.8
Requires-Dist: pyserial
Requires-Dist: python-osc
Requires-Dist: sliplib
